{
   "type": "FeatureCollection",
   "name": "georss",
   "crs": {
      "type": "name",
      "properties": {
      "name": "urn:ogc:def:crs:OGC:1.3:CRS84"
      }
    },
   "features": [
     {
       "type": "Feature",
       "properties": {
         "title": "Siaule",
         "description": "Siaule.",
         "link": "https://whc.unesco.org/en/list/1207"
       },
       "geometry": {
         "type": "Point",
         "coordinates": [23.370609, 55.85868]
       }
     },
     {
      "type": "Feature",
      "properties": {
        "title": "Riga",
        "description": "riga.",
        "link": "https://geoguessr-8509.s3.us-east-1.amazonaws.com/IMG_20230903_105641.jpg"
      },
      "geometry": {
        "type": "Point",
        "coordinates": [24.1, 56.954729]
      }
    },
    {
      "type": "Feature",
      "properties": {
        "title": "Riga",
        "description": "riga.",
        "link": "https://geoguessr-8509.s3.us-east-1.amazonaws.com/IMG_20230903_105641.jpg"
      },
      "geometry": {
        "type": "Point",
        "coordinates": [24.1, 56.954729]
      }
    },
    {
      "type": "Feature",
      "properties": {
        "title": "Riga",
        "description": "riga.",
        "link": "https://geoguessr-8509.s3.us-east-1.amazonaws.com/IMG_20230903_105641.jpg"
      },
      "geometry": {
        "type": "Point",
        "coordinates": [24.1, 56.954729]
      }
    },
    {
      "type": "Feature",
      "properties": {
        "title": "Riga",
        "description": "riga.",
        "link": "https://geoguessr-8509.s3.us-east-1.amazonaws.com/IMG_20230903_105641.jpg"
      },
      "geometry": {
        "type": "Point",
        "coordinates": [24.1, 56.954729]
      }
    },
    {
      "type": "Feature",
      "properties": {
        "title": "Riga",
        "description": "riga.",
        "link": "https://geoguessr-8509.s3.us-east-1.amazonaws.com/IMG_20230903_105641.jpg"
      },
      "geometry": {
        "type": "Point",
        "coordinates": [24.1, 56.954729]
      }
    },
    {
      "type": "Feature",
      "properties": {
        "title": "Riga",
        "description": "riga.",
        "link": "https://geoguessr-8509.s3.us-east-1.amazonaws.com/IMG_20230903_105641.jpg"
      },
      "geometry": {
        "type": "Point",
        "coordinates": [24.1, 56.954729]
      }
    },
    {
      "type": "Feature",
      "properties": {
        "title": "Riga",
        "description": "riga.",
        "link": "https://geoguessr-8509.s3.us-east-1.amazonaws.com/IMG_20230903_105641.jpg"
      },
      "geometry": {
        "type": "Point",
        "coordinates": [24.1, 56.954729]
      }
    },
    {
      "type": "Feature",
      "properties": {
        "title": "Riga",
        "description": "riga.",
        "link": "https://geoguessr-8509.s3.us-east-1.amazonaws.com/IMG_20230903_105641.jpg"
      },
      "geometry": {
        "type": "Point",
        "coordinates": [24.1, 56.954729]
      }
    }
   ]
 }
 